[
    {
        "imdb_id": "nm3387048",
        "name": "Pranav Mohanlal"
    },
    {
        "imdb_id": "nm9219502",
        "name": "Kalyani Priyadarshan"
    },
    {
        "imdb_id": "nm6697575",
        "name": "Darshana Rajendran"
    },
    {
        "imdb_id": "nm1066795",
        "name": "Vijayaraghavan"
    },
    {
        "imdb_id": "nm1434372",
        "name": "Johny Antony"
    },
    {
        "imdb_id": "nm4028151",
        "name": "Aju Varghese"
    },
    {
        "imdb_id": "nm8387510",
        "name": "Arun Kurian"
    },
    {
        "imdb_id": "nm13317139",
        "name": "Aswath Lal"
    },
    {
        "imdb_id": "nm8387513",
        "name": "Annu Antony"
    },
    {
        "imdb_id": "nm7489704",
        "name": "Abishek Joseph George"
    },
    {
        "imdb_id": "nm10406348",
        "name": "Ann Jameela Saleem"
    },
    {
        "imdb_id": "nm6946471",
        "name": "Megha Thomas"
    },
    {
        "imdb_id": "nm12642922",
        "name": "Sooraj Sun"
    },
    {
        "imdb_id": "nm12255412",
        "name": "Jojo Jose"
    },
    {
        "imdb_id": "nm13317140",
        "name": "Jishnu Sreekumar"
    },
    {
        "imdb_id": "nm13317141",
        "name": "Ajith Thomas Abraham"
    },
    {
        "imdb_id": "nm11335655",
        "name": "Kurian Joseph John"
    },
    {
        "imdb_id": "nm13317142",
        "name": "Sanjay Menon"
    },
    {
        "imdb_id": "nm8230797",
        "name": "Kalesh Ramanand"
    },
    {
        "imdb_id": "nm13317143",
        "name": "Kaushik M.V."
    },
    {
        "imdb_id": "nm12567686",
        "name": "Raja Rani Pandian"
    },
    {
        "imdb_id": "nm13317144",
        "name": "A.R. Raja Ganesh"
    },
    {
        "imdb_id": "nm13317145",
        "name": "Aravindan R."
    },
    {
        "imdb_id": "nm12473650",
        "name": "Ajeesh Jose"
    },
    {
        "imdb_id": "nm12558302",
        "name": "Shersha Sherief"
    },
    {
        "imdb_id": "nm13317146",
        "name": "Atul Ram Kumar"
    },
    {
        "imdb_id": "nm12207182",
        "name": "Sangeeth Prathap"
    },
    {
        "imdb_id": "nm5453661",
        "name": "Ramesh Menon"
    },
    {
        "imdb_id": "nm13457544",
        "name": "Nayan Rosh T M"
    },
    {
        "imdb_id": "nm11194976",
        "name": "Nikhil Nair"
    },
    {
        "imdb_id": "nm8782362",
        "name": "Serah Mathews"
    },
    {
        "imdb_id": "nm11861185",
        "name": "Thushara Pillai"
    },
    {
        "imdb_id": "nm12234581",
        "name": "Manjula Mohandas"
    },
    {
        "imdb_id": "nm13317820",
        "name": "Vijayakrishnan A.B."
    },
    {
        "imdb_id": "nm13317821",
        "name": "Chitra Kumar"
    },
    {
        "imdb_id": "nm11089993",
        "name": "Adithyan Chadrashekar"
    },
    {
        "imdb_id": "nm6440625",
        "name": "Anjali Nair"
    },
    {
        "imdb_id": "nm10379527",
        "name": "Meenakshi Raveendran"
    },
    {
        "imdb_id": "nm12375688",
        "name": "Maria Vincent"
    },
    {
        "imdb_id": "nm12757034",
        "name": "Aarsha Mohan"
    },
    {
        "imdb_id": "nm4975518",
        "name": "Prashant Nair"
    },
    {
        "imdb_id": "nm11887503",
        "name": "Adarsh Sukumaran"
    },
    {
        "imdb_id": "nm11053123",
        "name": "Shiva Hariharan"
    },
    {
        "imdb_id": "nm8166765",
        "name": "Shaun Romy"
    },
    {
        "imdb_id": "nm12759897",
        "name": "Shanu Kumar"
    },
    {
        "imdb_id": "nm13498069",
        "name": "Nabin Mahato"
    },
    {
        "imdb_id": "nm6550878",
        "name": "Mathukkutty"
    },
    {
        "imdb_id": "nm13399376",
        "name": "Anjali S. Nair"
    }
]