[
    {
        "imdb_id": "nm0048075",
        "name": "Manoj Bajpayee"
    },
    {
        "imdb_id": "nm3190246",
        "name": "Richa Chadha"
    },
    {
        "imdb_id": "nm1596350",
        "name": "Nawazuddin Siddiqui"
    },
    {
        "imdb_id": "nm0223606",
        "name": "Tigmanshu Dhulia"
    },
    {
        "imdb_id": "nm0451239",
        "name": "Jameel Khan"
    },
    {
        "imdb_id": "nm0592795",
        "name": "Piyush Mishra"
    },
    {
        "imdb_id": "nm4188433",
        "name": "Jaideep Ahlawat"
    },
    {
        "imdb_id": "nm4806622",
        "name": "Huma Qureshi"
    },
    {
        "imdb_id": "nm5113220",
        "name": "Zeishan Quadri"
    },
    {
        "imdb_id": "nm1479650",
        "name": "Vipin Sharma"
    },
    {
        "imdb_id": "nm3864624",
        "name": "Satyakam Anand"
    },
    {
        "imdb_id": "nm4748818",
        "name": "Aditya Kumar"
    },
    {
        "imdb_id": "nm3822770",
        "name": "Rajkummar Rao"
    },
    {
        "imdb_id": "nm1277547",
        "name": "Vineet Kumar Singh"
    },
    {
        "imdb_id": "nm4435813",
        "name": "Sankalp Acharekar"
    },
    {
        "imdb_id": "nm10826097",
        "name": "Aditya"
    },
    {
        "imdb_id": "nm10826076",
        "name": "Akshat"
    },
    {
        "imdb_id": "nm10826095",
        "name": "Hasrat Ali"
    },
    {
        "imdb_id": "nm10826060",
        "name": "Mohammed Azam Ansari"
    },
    {
        "imdb_id": "nm3035236",
        "name": "Vasan Bala"
    },
    {
        "imdb_id": "nm5129212",
        "name": "Mahesh Balraj"
    },
    {
        "imdb_id": "nm4488932",
        "name": "Rajat Bhagat"
    },
    {
        "imdb_id": "nm10826040",
        "name": "Vidya Bhushan"
    },
    {
        "imdb_id": "nm10826049",
        "name": "Bobby"
    },
    {
        "imdb_id": "nm10826072",
        "name": "Niranjan Chaubey"
    },
    {
        "imdb_id": "nm2535507",
        "name": "Mukesh Chhabra"
    },
    {
        "imdb_id": "nm10826088",
        "name": "Tarzan Dada"
    },
    {
        "imdb_id": "nm10826059",
        "name": "Sujata Das"
    },
    {
        "imdb_id": "nm10826047",
        "name": "Dulaari Devi"
    },
    {
        "imdb_id": "nm7436747",
        "name": "Shreedhar Dubey"
    },
    {
        "imdb_id": "nm4435585",
        "name": "Karuna Dutt"
    },
    {
        "imdb_id": "nm10826093",
        "name": "Upal Dutta"
    },
    {
        "imdb_id": "nm5200693",
        "name": "Vivek Ghamande"
    },
    {
        "imdb_id": "nm10826042",
        "name": "Amitabh Kishen Ghanekar"
    },
    {
        "imdb_id": "nm10826043",
        "name": "Hemangini Ghanekar"
    },
    {
        "imdb_id": "nm10826106",
        "name": "Neeraj Ghaywan"
    },
    {
        "imdb_id": "nm10826113",
        "name": "Radhe Shyam Giri"
    },
    {
        "imdb_id": "nm10826077",
        "name": "Guddu"
    },
    {
        "imdb_id": "nm10826084",
        "name": "Siddharth Gupt"
    },
    {
        "imdb_id": "nm4495315",
        "name": "Naman Jain"
    },
    {
        "imdb_id": "nm4839358",
        "name": "Anurita Jha"
    },
    {
        "imdb_id": "nm10826100",
        "name": "Lali Ji"
    },
    {
        "imdb_id": "nm10826044",
        "name": "Chandan Kaif"
    },
    {
        "imdb_id": "nm10826089",
        "name": "Sameer Kamble"
    },
    {
        "imdb_id": "nm10826066",
        "name": "Omprakash Kashyap"
    },
    {
        "imdb_id": "nm5817249",
        "name": "Vicky Kaushal"
    },
    {
        "imdb_id": "nm10826045",
        "name": "Zafar Khan"
    },
    {
        "imdb_id": "nm1390115",
        "name": "Harish Khanna"
    },
    {
        "imdb_id": "nm1227999",
        "name": "Aditya Kumar"
    },
    {
        "imdb_id": "nm10826102",
        "name": "Amit Kumar"
    },
    {
        "imdb_id": "nm2715305",
        "name": "Murari Kumar"
    },
    {
        "imdb_id": "nm10826046",
        "name": "Sumit Kumar"
    },
    {
        "imdb_id": "nm10826041",
        "name": "Vishnu Kumar"
    },
    {
        "imdb_id": "nm10826048",
        "name": "Vishnu Kunwar"
    },
    {
        "imdb_id": "nm10826092",
        "name": "Ram Lakhan"
    },
    {
        "imdb_id": "nm10826112",
        "name": "Mahesh"
    },
    {
        "imdb_id": "nm6763126",
        "name": "Faisal Malik"
    },
    {
        "imdb_id": "nm10826075",
        "name": "Ashtabhuja Mishra"
    },
    {
        "imdb_id": "nm10826058",
        "name": "Sudhanshu Mishra"
    },
    {
        "imdb_id": "nm10826062",
        "name": "Vinay Mishra"
    },
    {
        "imdb_id": "nm1665339",
        "name": "Pranay Narayan"
    },
    {
        "imdb_id": "nm10826067",
        "name": "Bhola Nath"
    },
    {
        "imdb_id": "nm10826103",
        "name": "Kaushal Nigel"
    },
    {
        "imdb_id": "nm10826109",
        "name": "Balram Pandey"
    },
    {
        "imdb_id": "nm10826110",
        "name": "Ila Pandey"
    },
    {
        "imdb_id": "nm1221483",
        "name": "Pramod Pathak"
    },
    {
        "imdb_id": "nm10826057",
        "name": "Suman Pathak"
    },
    {
        "imdb_id": "nm10826063",
        "name": "Sankata Prasad"
    },
    {
        "imdb_id": "nm4556476",
        "name": "Syed Zeeshan Qadri"
    },
    {
        "imdb_id": "nm10826080",
        "name": "Tilak Raj"
    },
    {
        "imdb_id": "nm3771295",
        "name": "Vijesh Rajan"
    },
    {
        "imdb_id": "nm10826082",
        "name": "Amritraj Rana"
    },
    {
        "imdb_id": "nm10826064",
        "name": "Ravi"
    },
    {
        "imdb_id": "nm10826068",
        "name": "Khan Saab"
    },
    {
        "imdb_id": "nm10826107",
        "name": "Veena Sahay"
    },
    {
        "imdb_id": "nm1032614",
        "name": "Reema Sen"
    },
    {
        "imdb_id": "nm10826039",
        "name": "Ashfaque Shaikh"
    },
    {
        "imdb_id": "nm9818830",
        "name": "Salim M. Shaikh"
    },
    {
        "imdb_id": "nm10036672",
        "name": "Amit Sharma"
    },
    {
        "imdb_id": "nm10826083",
        "name": "Gaurav Sharma"
    },
    {
        "imdb_id": "nm9856002",
        "name": "Gaurav Sharma"
    },
    {
        "imdb_id": "nm6422090",
        "name": "Rajesh Kumar Sharma"
    },
    {
        "imdb_id": "nm10826104",
        "name": "Shlok Sharma"
    },
    {
        "imdb_id": "nm10826094",
        "name": "Tez Bahadur Sharma"
    },
    {
        "imdb_id": "nm1004985",
        "name": "Yashpal Sharma"
    },
    {
        "imdb_id": "nm10826078",
        "name": "Zahir Sheikh"
    },
    {
        "imdb_id": "nm10826073",
        "name": "Suhas Shirsat"
    },
    {
        "imdb_id": "nm10826054",
        "name": "Shivam"
    },
    {
        "imdb_id": "nm10826070",
        "name": "Shubham"
    },
    {
        "imdb_id": "nm10826055",
        "name": "Vijay Shukla"
    },
    {
        "imdb_id": "nm10826069",
        "name": "Janmajaya Singh"
    },
    {
        "imdb_id": "nm10826085",
        "name": "Nitin Raj Singh"
    },
    {
        "imdb_id": "nm10826090",
        "name": "Nityanand Singh"
    },
    {
        "imdb_id": "nm7372243",
        "name": "Pawan Singh"
    },
    {
        "imdb_id": "nm10826050",
        "name": "Ram Raksha Singh"
    },
    {
        "imdb_id": "nm7916099",
        "name": "Sanjay Singh"
    },
    {
        "imdb_id": "nm10826101",
        "name": "Santosh Singh"
    },
    {
        "imdb_id": "nm10826081",
        "name": "Vivek Singh"
    },
    {
        "imdb_id": "nm4518724",
        "name": "Akash Sinha"
    },
    {
        "imdb_id": "nm10826051",
        "name": "Varun Sinha"
    },
    {
        "imdb_id": "nm3720865",
        "name": "Suhas Sirsat"
    },
    {
        "imdb_id": "nm10826056",
        "name": "Praveen Sisodia"
    },
    {
        "imdb_id": "nm4606894",
        "name": "Pravin Singh Sisodia"
    },
    {
        "imdb_id": "nm10826065",
        "name": "Amreesh Srivastava"
    },
    {
        "imdb_id": "nm10826053",
        "name": "Anup Srivastava"
    },
    {
        "imdb_id": "nm4867316",
        "name": "Shilpa Srivastava"
    },
    {
        "imdb_id": "nm10826096",
        "name": "Mamta Tiwari"
    },
    {
        "imdb_id": "nm10826099",
        "name": "Prerna Tiwari"
    },
    {
        "imdb_id": "nm10826061",
        "name": "Rajnikant Trigul"
    },
    {
        "imdb_id": "nm12288378",
        "name": "Heramba Shankar Tripathi"
    },
    {
        "imdb_id": "nm2690647",
        "name": "Pankaj Tripathi"
    },
    {
        "imdb_id": "nm2768833",
        "name": "Rati Shankar Tripathi"
    },
    {
        "imdb_id": "nm10826091",
        "name": "Vijay Tripathi"
    },
    {
        "imdb_id": "nm10826071",
        "name": "Utkarsh"
    },
    {
        "imdb_id": "nm10826074",
        "name": "Sanjeeva Vats"
    },
    {
        "imdb_id": "nm10826086",
        "name": "Sagar Verma"
    },
    {
        "imdb_id": "nm6451984",
        "name": "Jack Wayne"
    },
    {
        "imdb_id": "nm10826098",
        "name": "Luv Yadav"
    },
    {
        "imdb_id": "nm10826052",
        "name": "Rambhu Yadav"
    },
    {
        "imdb_id": "nm10826079",
        "name": "Rashmi Yadav"
    },
    {
        "imdb_id": "nm10826111",
        "name": "Tripurari Yadav"
    },
    {
        "imdb_id": "nm10826108",
        "name": "Kiran Yaday"
    },
    {
        "imdb_id": "nm4731845",
        "name": "Rohit Pandey"
    },
    {
        "imdb_id": "nm1019127",
        "name": "Sanjeeva Vatsa"
    }
]