[
    {
        "imdb_id": "nm3807965",
        "name": "Sundeep Kishan"
    },
    {
        "imdb_id": "nm5036793",
        "name": "Sri"
    },
    {
        "imdb_id": "nm5294556",
        "name": "Regina Cassandra"
    },
    {
        "imdb_id": "nm1706602",
        "name": "Charlie"
    },
    {
        "imdb_id": "nm6106368",
        "name": "Munishkanth"
    },
    {
        "imdb_id": "nm9012886",
        "name": "Sha Ra"
    },
    {
        "imdb_id": "nm10154962",
        "name": "Arun Alexander"
    },
    {
        "imdb_id": "nm8995897",
        "name": "Madhusudhan"
    },
    {
        "imdb_id": "nm8995898",
        "name": "Ravi Venkat"
    },
    {
        "imdb_id": "nm7925166",
        "name": "Sai Dheena"
    },
    {
        "imdb_id": "nm8995909",
        "name": "Tiger Thangadurai"
    },
    {
        "imdb_id": "nm5324114",
        "name": "Karthik Yogi"
    },
    {
        "imdb_id": "nm8995902",
        "name": "Amresh"
    },
    {
        "imdb_id": "nm8995905",
        "name": "Vivek Prasanna"
    },
    {
        "imdb_id": "nm8995900",
        "name": "Sathish Kumar"
    },
    {
        "imdb_id": "nm8995901",
        "name": "Saravanan"
    },
    {
        "imdb_id": "nm8995903",
        "name": "R.S. Karthik"
    },
    {
        "imdb_id": "nm8995904",
        "name": "Dhuruva"
    },
    {
        "imdb_id": "nm0762839",
        "name": "Jai Sankar"
    },
    {
        "imdb_id": "nm6340762",
        "name": "Rekha Suresh"
    },
    {
        "imdb_id": "nm4848482",
        "name": "Rajini"
    },
    {
        "imdb_id": "nm8995906",
        "name": "Vanitha"
    },
    {
        "imdb_id": "nm5326891",
        "name": "Ashish"
    },
    {
        "imdb_id": "nm8995907",
        "name": "Arush"
    },
    {
        "imdb_id": "nm6168639",
        "name": "Siranjeevi"
    },
    {
        "imdb_id": "nm8995908",
        "name": "Vinoth"
    },
    {
        "imdb_id": "nm8995910",
        "name": "Vishweshwar Rao"
    },
    {
        "imdb_id": "nm8995911",
        "name": "SaravanaVel"
    },
    {
        "imdb_id": "nm8995912",
        "name": "Gopi Raam"
    },
    {
        "imdb_id": "nm8995913",
        "name": "Balaji"
    },
    {
        "imdb_id": "nm8995914",
        "name": "Mak Mani"
    },
    {
        "imdb_id": "nm8995915",
        "name": "Varun"
    },
    {
        "imdb_id": "nm8995916",
        "name": "Chandru"
    },
    {
        "imdb_id": "nm8995917",
        "name": "Jana"
    },
    {
        "imdb_id": "nm6653784",
        "name": "Subramani"
    },
    {
        "imdb_id": "nm8995919",
        "name": "Baskar"
    },
    {
        "imdb_id": "nm5801106",
        "name": "Thirukumaran"
    },
    {
        "imdb_id": "nm8995920",
        "name": "Hari"
    },
    {
        "imdb_id": "nm8995921",
        "name": "Karthikeyan"
    },
    {
        "imdb_id": "nm8995922",
        "name": "Shanmugam"
    },
    {
        "imdb_id": "nm8995899",
        "name": "Arun"
    },
    {
        "imdb_id": "nm8995918",
        "name": "Subramani Pt"
    },
    {
        "imdb_id": "nm6653781",
        "name": "Pasupathy Raj"
    }
]